ez_openai/__init__.py
ez_openai/decorator.py
ez_openai-0.0.7.dist-info/LICENSE
ez_openai-0.0.7.dist-info/METADATA
ez_openai-0.0.7.dist-info/WHEEL
ez_openai-0.0.7.dist-info/RECORD
