Metadata-Version: 2.1
Name: ez-openai
Version: 0.0.7
Summary: A more reasonable OpenAI API.
Home-page: https://github.com/skorokithakis/ez-openai/
License: AGPL-3.0-or-later
Author: Stavros Korokithakis
Author-email: hi@stavros.io
Requires-Python: >=3.8,<4
Classifier: License :: OSI Approved :: GNU Affero General Public License v3 or later (AGPLv3+)
Classifier: Programming Language :: Python :: 3
Classifier: Programming Language :: Python :: 3.8
Classifier: Programming Language :: Python :: 3.9
Classifier: Programming Language :: Python :: 3.10
Classifier: Programming Language :: Python :: 3.11
Classifier: Programming Language :: Python :: 3.12
Requires-Dist: openai (>=1.3.5)
Project-URL: Repository, https://github.com/skorokithakis/ez-openai/
